superduper_pillow/__init__.py
superduper_pillow/encoder.py
superduper_pillow-0.10.0.dist-info/licenses/LICENSE
superduper_pillow-0.10.0.dist-info/METADATA
superduper_pillow-0.10.0.dist-info/WHEEL
superduper_pillow-0.10.0.dist-info/top_level.txt
superduper_pillow-0.10.0.dist-info/RECORD
