Metadata-Version: 2.4
Name: superduper_pillow
Version: 0.10.0
Summary: SuperDuper Pillow is a plugin for SuperDuper that provides support for Pillow.
Maintainer-email: "superduper.io, Inc." <opensource@superduper.io>
License: 
Project-URL: homepage, https://superduper.io
Project-URL: documentation, https://docs.superduper.io/docs/intro
Project-URL: source, https://github.com/superduper-io/superduper
Keywords: databases,mongodb,data-science,machine-learning,mlops,vector-database,ai
Requires-Python: >=3.10
License-File: LICENSE
Requires-Dist: pillow>=10.2.0
Provides-Extra: test
Requires-Dist: ibis-framework[sqlite]>=5.1.0; extra == "test"
Dynamic: license-file
